travdeploy/__init__.py
travdeploy/scripts/__init__.py
travdeploy/scripts/cli.py
travdeploy-0.0.9.dist-info/METADATA
travdeploy-0.0.9.dist-info/RECORD
travdeploy-0.0.9.dist-info/WHEEL
travdeploy-0.0.9.dist-info/entry_points.txt
travdeploy-0.0.9.dist-info/top_level.txt
