Metadata-Version: 2.1
Name: travdeploy
Version: 0.0.9
Summary: Skeleton of a Python package
Home-page: https://github.com/jacquestardie/travdeploy
Author: Jacques Tardie
Author-email: hi@jacquestardie.org
License: MIT
Platform: UNKNOWN
Provides-Extra: test
Requires-Dist: click
Provides-Extra: test
Requires-Dist: pytest; extra == 'test'
Requires-Dist: pytest-cov; extra == 'test'
Requires-Dist: codecov; extra == 'test'
